cellSP/__init__.py
cellSP/characterize/__init__.py
cellSP/characterize/_bicluster.py
cellSP/characterize/_instant.py
cellSP/characterize/_sprawl.py
cellSP/characterize/_utils.py
cellSP/datasets/__init__.py
cellSP/datasets/_datasets.py
cellSP/geo/__init__.py
cellSP/geo/_geo.py
cellSP/io/__init__.py
cellSP/io/_io.py
cellSP/model/__init__.py
cellSP/model/_model.py
cellSP/preprocessing/__init__.py
cellSP/preprocessing/_extrapolate.py
cellSP/preprocessing/_impute.py
cellSP/visualisation/__init__.py
cellSP/visualisation/_circularize.py
cellSP/visualisation/_compare.py
cellSP/visualisation/_enrichment.py
cellSP/visualisation/_raw.py
cellSP/visualisation/_report.py
cellSP/visualisation/_validation.py
cellsp-2.2.2.dist-info/licenses/LICENSE
cellsp-2.2.2.dist-info/METADATA
cellsp-2.2.2.dist-info/WHEEL
cellsp-2.2.2.dist-info/top_level.txt
cellsp-2.2.2.dist-info/RECORD
