Metadata-Version: 2.4
Name: cellSP
Version: 2.2.2
Summary: cellSP.
Author-email: Bhavay Aggarwal <baggarwal9@gatech.edu>
License-Expression: MIT
Requires-Python: >=3.9
License-File: LICENSE
Requires-Dist: contourpy>=1.1.1
Requires-Dist: cycler>=0.12.1
Requires-Dist: et-xmlfile>=1.1.0
Requires-Dist: fonttools>=4.43.1
Requires-Dist: joblib>=1.3.2
Requires-Dist: kiwisolver>=1.4.5
Requires-Dist: matplotlib>=3.8.0
Requires-Dist: openpyxl>=3.1.2
Requires-Dist: packaging>=23.2
Requires-Dist: pillow>=10.1.0
Requires-Dist: psutil>=5.9.6
Requires-Dist: pyparsing>=3.1.1
Requires-Dist: scikit-learn>=1.3.2
Requires-Dist: scipy>=1.11.3
Requires-Dist: threadpoolctl>=3.2.0
Requires-Dist: pandas>=2.1.4
Requires-Dist: anndata>=0.10.4
Requires-Dist: networkx>=3.2.1
Requires-Dist: sc-instant>=1.2.1
Requires-Dist: tangram-sc>=1.0.4
Requires-Dist: magic-impute>=3.0.0
Requires-Dist: smallestenclosingcircle>=0.0.1
Requires-Dist: requests>=2.32.3
Requires-Dist: adjustText>=1.3.0
Requires-Dist: Bottleneck>=1.4.2
Requires-Dist: shapely>=2.0.6
Requires-Dist: shap>=0.46.0
Requires-Dist: umap-learn>=0.5.7
Dynamic: license-file
